{
  "tag": "2022-10-17_144602",
  "event": {
    "event_type": "touch",
    "log_lines": null,
    "x": null,
    "y": null,
    "view": {
      "package": "com.ubercab.driver",
      "visible": true,
      "checkable": false,
      "child_count": 0,
      "editable": false,
      "clickable": true,
      "is_password": false,
      "focusable": true,
      "enabled": true,
      "content_description": null,
      "children": [],
      "focused": false,
      "bounds": [
        [
          110,
          1337
        ],
        [
          459,
          1469
        ]
      ],
      "resource_id": null,
      "checked": false,
      "text": "Plus small Gift card",
      "class": "android.widget.Button",
      "scrollable": false,
      "selected": false,
      "long_clickable": false,
      "parent": 46,
      "temp_id": 47,
      "size": "349*132",
      "signature": "[class]android.widget.Button[resource_id]None[text]Plus small Gift card[enabled,,]",
      "view_str": "8e246a572d36189be006d9efeac72dda"
    }
  },
  "start_state": "ad09117e2763271add2cd1fd08de25ee",
  "stop_state": "ad09117e2763271add2cd1fd08de25ee",
  "event_str": "TouchEvent(state=ad09117e2763271add2cd1fd08de25ee, view=8e246a572d36189be006d9efeac72dda(CarbonActivity/Button-Plus small))"
}