{
  "tag": "2022-10-17_140424",
  "event": {
    "event_type": "touch",
    "log_lines": null,
    "x": null,
    "y": null,
    "view": {
      "package": "com.ubercab.driver",
      "visible": true,
      "checkable": false,
      "child_count": 0,
      "editable": false,
      "clickable": false,
      "is_password": false,
      "focusable": false,
      "enabled": true,
      "content_description": null,
      "children": [],
      "focused": false,
      "bounds": [
        [
          165,
          217
        ],
        [
          308,
          301
        ]
      ],
      "resource_id": null,
      "checked": false,
      "text": "Help",
      "class": "android.widget.TextView",
      "scrollable": false,
      "selected": false,
      "long_clickable": false,
      "parent": 23,
      "temp_id": 25,
      "size": "143*84",
      "signature": "[class]android.widget.TextView[resource_id]None[text]Help[enabled,,]",
      "view_str": "309eff540515266900ddd07b944b2a15"
    }
  },
  "start_state": "c749836e164fdd772d6e7b43a31a7e08",
  "stop_state": "c749836e164fdd772d6e7b43a31a7e08",
  "event_str": "TouchEvent(state=c749836e164fdd772d6e7b43a31a7e08, view=309eff540515266900ddd07b944b2a15(CarbonActivity/TextView-Help))"
}