{
  "tag": "2022-10-17_140430",
  "event": {
    "event_type": "touch",
    "log_lines": null,
    "x": null,
    "y": null,
    "view": {
      "package": "com.ubercab.driver",
      "visible": true,
      "checkable": false,
      "child_count": 0,
      "editable": false,
      "clickable": true,
      "is_password": false,
      "focusable": true,
      "enabled": true,
      "content_description": "Back",
      "children": [],
      "focused": false,
      "bounds": [
        [
          0,
          182
        ],
        [
          154,
          336
        ]
      ],
      "resource_id": null,
      "checked": false,
      "text": null,
      "class": "android.widget.ImageButton",
      "scrollable": false,
      "selected": false,
      "long_clickable": false,
      "parent": 23,
      "temp_id": 24,
      "size": "154*154",
      "signature": "[class]android.widget.ImageButton[resource_id]None[text]None[enabled,,]",
      "view_str": "a20d8b8bc61857738f6db1aee51e68e7"
    }
  },
  "start_state": "c749836e164fdd772d6e7b43a31a7e08",
  "stop_state": "f4f5a883f57628e2b06ef068d0f5446e",
  "event_str": "TouchEvent(state=c749836e164fdd772d6e7b43a31a7e08, view=a20d8b8bc61857738f6db1aee51e68e7(CarbonActivity/ImageButton-))"
}